bitctrl/Bitctrl.py
bitctrl/__init__.py
bitctrl-0.2.dist-info/LICENSE
bitctrl-0.2.dist-info/METADATA
bitctrl-0.2.dist-info/WHEEL
bitctrl-0.2.dist-info/top_level.txt
bitctrl-0.2.dist-info/RECORD
