Metadata-Version: 2.1
Name: bitctrl
Version: 0.2
Summary: Turn your microbit into a controller
Home-page: UNKNOWN
Author: momea007
Author-email: momea007@hotmail.com
License: MIT
Keywords: microbit
Platform: UNKNOWN
Requires-Dist: pyserial
Requires-Dist: keyboard
